Monarchdos/__init__.py
Monarchdos/monarchdos.py
Monarchdos-1.0.1.dist-info/METADATA
Monarchdos-1.0.1.dist-info/WHEEL
Monarchdos-1.0.1.dist-info/entry_points.txt
Monarchdos-1.0.1.dist-info/top_level.txt
Monarchdos-1.0.1.dist-info/RECORD
