Metadata-Version: 2.1
Name: Monarchdos
Version: 1.0.1
Summary: Monarchdos
Home-page: UNKNOWN
Author: Monarchdos
Author-email: admin@ayfre.com
License: UNKNOWN
Platform: any
Requires-Dist: requests
